parastat/__init__.py
parastat/cli.py
parastat/decomp.py
parastat/errors.py
parastat/formula.py
parastat/io.py
parastat/models.py
parastat/resampling.py
parastat/session.py
parastat/types.py
parastat/utils.py
parastat-0.1.1.dist-info/licenses/LICENSE
parastat-0.1.1.dist-info/METADATA
parastat-0.1.1.dist-info/WHEEL
parastat-0.1.1.dist-info/entry_points.txt
parastat-0.1.1.dist-info/top_level.txt
parastat-0.1.1.dist-info/RECORD
