Metadata-Version: 2.4
Name: parastat
Version: 0.1.1
Summary: Parastat: CPU/GPU 并行的数据统计分析库（OLS/GLM、PCA/SVD、Bootstrap/MC）
Author-email: Yibo <3895712449@qq.com>
License: MIT
Project-URL: Homepage, https://gravatar.com/observantgentlemen213bfd8acf
Project-URL: Repository, https://github.com/fept-2024/parastat
Project-URL: Issues, https://github.com/fept-2024/parastat/issues
Requires-Python: >=3.8
License-File: LICENSE
Requires-Dist: numpy>=1.22
Requires-Dist: pandas>=1.5
Provides-Extra: gpu
Requires-Dist: cupy-cuda12x; extra == "gpu"
Provides-Extra: parquet
Requires-Dist: pyarrow>=9; extra == "parquet"
Provides-Extra: dev
Requires-Dist: pytest>=7; extra == "dev"
Requires-Dist: ruff>=0.5; extra == "dev"
Requires-Dist: mypy>=1.0; extra == "dev"
Dynamic: license-file
